pyqt_resource_helper/__init__.py
pyqt_resource_helper/pyqtResourceHelper.py
pyqt_resource_helper-0.0.14.dist-info/LICENSE
pyqt_resource_helper-0.0.14.dist-info/METADATA
pyqt_resource_helper-0.0.14.dist-info/WHEEL
pyqt_resource_helper-0.0.14.dist-info/top_level.txt
pyqt_resource_helper-0.0.14.dist-info/RECORD
