Metadata-Version: 2.1
Name: pyqt-resource-helper
Version: 0.0.14
Summary: Setting icons, stylesheets of imported packages based on main module to prevent FileNotFoundError
Home-page: https://github.com/yjg30737/pyqt-resource-helper.git
Author: Jung Gyu Yoon
Author-email: yjg30737@gmail.com
License: MIT
License-File: LICENSE
Requires-Dist: PyQt5 (>=5.8)
